dibs/__init__.py
dibs/graph_utils.py
dibs/kernel.py
dibs/metrics.py
dibs/target.py
dibs/inference/__init__.py
dibs/inference/dibs.py
dibs/inference/svgd.py
dibs/models/__init__.py
dibs/models/graph.py
dibs/models/linearGaussian.py
dibs/models/nonlinearGaussian.py
dibs/utils/__init__.py
dibs/utils/func.py
dibs/utils/tree.py
dibs/utils/visualize.py
dibs_lib-1.3.3.dist-info/LICENCE
dibs_lib-1.3.3.dist-info/METADATA
dibs_lib-1.3.3.dist-info/WHEEL
dibs_lib-1.3.3.dist-info/top_level.txt
dibs_lib-1.3.3.dist-info/RECORD
