Metadata-Version: 2.1
Name: dibs-lib
Version: 1.3.3
Summary: DiBS: Differentiable Bayesian Structure Learning
Home-page: https://github.com/larslorch/dibs
Author: Lars Lorch
Author-email: lars.lorch@inf.ethz.ch
Classifier: Programming Language :: Python :: 3
Classifier: License :: OSI Approved :: MIT License
Classifier: Operating System :: OS Independent
License-File: LICENCE
Requires-Dist: jax >=0.3.17
Requires-Dist: jaxlib >=0.3.14
Requires-Dist: numpy
Requires-Dist: igraph
Requires-Dist: imageio
Requires-Dist: jupyter
Requires-Dist: tqdm
Requires-Dist: matplotlib
Requires-Dist: scikit-learn
